{
  "resourceType": "Observation",
  "id": "observation-braden-scale",
  "meta": {
    "profile": [
      "https://clinyqai.github.io/open-nursing-core-ig/StructureDefinition/onc-braden-scale-assessment"
    ]
  },
  "status": "final",
  "category": [
    {
      "coding": [
        {
          "code": "survey",
          "system": "http://terminology.hl7.org/CodeSystem/observation-category"
        }
      ]
    }
  ],
  "code": {
    "coding": [
      {
        "code": "braden-total-score",
        "system": "https://clinyqai.github.io/open-nursing-core-ig/CodeSystem/onc-observation-codes",
        "display": "Braden Total Score"
      }
    ]
  },
  "valueQuantity": {
    "unit": "{score}",
    "system": "http://unitsofmeasure.org",
    "code": "1",
    "value": 18
  },
  "component": [
    {
      "code": {
        "coding": [
          {
            "code": "braden-sensory",
            "system": "https://clinyqai.github.io/open-nursing-core-ig/CodeSystem/onc-observation-codes",
            "display": "Braden Sensory Perception"
          }
        ]
      },
      "valueQuantity": {
        "value": 3,
        "unit": "{score}",
        "system": "http://unitsofmeasure.org",
        "code": "1"
      }
    },
    {
      "code": {
        "coding": [
          {
            "code": "braden-moisture",
            "system": "https://clinyqai.github.io/open-nursing-core-ig/CodeSystem/onc-observation-codes",
            "display": "Braden Moisture"
          }
        ]
      },
      "valueQuantity": {
        "value": 4,
        "unit": "{score}",
        "system": "http://unitsofmeasure.org",
        "code": "1"
      }
    },
    {
      "code": {
        "coding": [
          {
            "code": "braden-activity",
            "system": "https://clinyqai.github.io/open-nursing-core-ig/CodeSystem/onc-observation-codes",
            "display": "Braden Activity"
          }
        ]
      },
      "valueQuantity": {
        "value": 2,
        "unit": "{score}",
        "system": "http://unitsofmeasure.org",
        "code": "1"
      }
    },
    {
      "code": {
        "coding": [
          {
            "code": "braden-mobility",
            "system": "https://clinyqai.github.io/open-nursing-core-ig/CodeSystem/onc-observation-codes",
            "display": "Braden Mobility"
          }
        ]
      },
      "valueQuantity": {
        "value": 3,
        "unit": "{score}",
        "system": "http://unitsofmeasure.org",
        "code": "1"
      }
    },
    {
      "code": {
        "coding": [
          {
            "code": "braden-nutrition",
            "system": "https://clinyqai.github.io/open-nursing-core-ig/CodeSystem/onc-observation-codes",
            "display": "Braden Nutrition"
          }
        ]
      },
      "valueQuantity": {
        "value": 3,
        "unit": "{score}",
        "system": "http://unitsofmeasure.org",
        "code": "1"
      }
    },
    {
      "code": {
        "coding": [
          {
            "code": "braden-friction",
            "system": "https://clinyqai.github.io/open-nursing-core-ig/CodeSystem/onc-observation-codes",
            "display": "Braden Friction/Shear"
          }
        ]
      },
      "valueQuantity": {
        "value": 3,
        "unit": "{score}",
        "system": "http://unitsofmeasure.org",
        "code": "1"
      }
    }
  ],
  "subject": {
    "reference": "Patient/patient-example-jane"
  },
  "performer": [
    {
      "reference": "Practitioner/practitioner-example"
    }
  ]
}
